torchic_tab_heuristic/__init__.py
torchic_tab_heuristic/annotation.py
torchic_tab_heuristic/cea_calculation.py
torchic_tab_heuristic/config.py
torchic_tab_heuristic/context_score.py
torchic_tab_heuristic/cpa_calculation.py
torchic_tab_heuristic/cta_calculation.py
torchic_tab_heuristic/data_load.py
torchic_tab_heuristic/data_load_v2.py
torchic_tab_heuristic/entity_classes.py
torchic_tab_heuristic/lookup.py
torchic_tab_heuristic/preprocessing.py
torchic_tab_heuristic/task_calculation_tfood.py
torchic_tab_heuristic/task_calculation_wd.py
torchic_tab_heuristic/td_calculation.py
torchic_tab_heuristic/utils.py
torchic_tab_heuristic/wikidata_searcher.py
torchic_tab_heuristic-0.1.2.dist-info/licenses/LICENSE
torchic_tab_heuristic-0.1.2.dist-info/METADATA
torchic_tab_heuristic-0.1.2.dist-info/WHEEL
torchic_tab_heuristic-0.1.2.dist-info/top_level.txt
torchic_tab_heuristic-0.1.2.dist-info/RECORD
