Metadata-Version: 2.4
Name: torchic_tab_heuristic
Version: 0.1.2
Summary: TorchicTab-Heuristic: Semantic Table Annotation with Wikidata
Home-page: https://github.com/dtai-kg/TorchicTab-Heuristic
Author: Ioannis Dasoulas
Author-email: ioannis.dasoulas@kuleuven.be
License: Apache-2.0
Classifier: Programming Language :: Python :: 3
Classifier: License :: OSI Approved :: Apache Software License
Classifier: Intended Audience :: Developers
Classifier: Intended Audience :: Science/Research
Classifier: Natural Language :: English
Requires-Python: >=3.9, <3.12
License-File: LICENSE
Requires-Dist: elasticsearch==8.3.1
Requires-Dist: pandas==2.2.1
Requires-Dist: nltk==3.8.1
Requires-Dist: sparqlwrapper==2.0.0
Requires-Dist: spacy==3.7.2
Requires-Dist: beautifulsoup4==4.12.2
Requires-Dist: ftfy==6.1.3
Requires-Dist: levenshtein==0.25.1
Requires-Dist: commonregex==1.5.4
Dynamic: author
Dynamic: author-email
Dynamic: classifier
Dynamic: description
Dynamic: description-content-type
Dynamic: home-page
Dynamic: license
Dynamic: license-file
Dynamic: requires-dist
Dynamic: requires-python
Dynamic: summary
